bdms_rucio_policy/__init__.py
bdms_rucio_policy/_version.py
bdms_rucio_policy/conftest.py
bdms_rucio_policy/lfn2pfn.py
bdms_rucio_policy/permission.py
bdms_rucio_policy/schema.py
bdms_rucio_policy/scope.py
bdms_rucio_policy/tests/__init__.py
bdms_rucio_policy/tests/test_algorithms.py
bdms_rucio_policy/tests/test_permissions.py
bdms_rucio_policy/tests/test_schema.py
bdms_rucio_policy/tests/resources/rucio.cfg
ctao_bdms_rucio_policy-0.2.2.dist-info/METADATA
ctao_bdms_rucio_policy-0.2.2.dist-info/WHEEL
ctao_bdms_rucio_policy-0.2.2.dist-info/top_level.txt
ctao_bdms_rucio_policy-0.2.2.dist-info/RECORD
