Metadata-Version: 2.4
Name: ctao-bdms-rucio-policy
Version: 0.2.2
Summary: CTAO RUCIO policy package
Author-email: Maximilian Linhoff <maximilian.linhoff@tu-dortmund.de>
License: BSD-3-Clause
Project-URL: repository, https://gitlab.cta-observatory.org/cta-computing/dpps/bdms/bdms-rucio-policy
Requires-Python: >=3.9
Provides-Extra: test
Requires-Dist: pytest; extra == "test"
Requires-Dist: pytest-cov; extra == "test"
Requires-Dist: rucio~=38.2; extra == "test"
Provides-Extra: all
Requires-Dist: ctao-bdms-rucio-policy[test]; extra == "all"
